cueBeam-0.0.1.dist-info/DESCRIPTION.rst
cueBeam-0.0.1.dist-info/METADATA
cueBeam-0.0.1.dist-info/RECORD
cueBeam-0.0.1.dist-info/WHEEL
cueBeam-0.0.1.dist-info/metadata.json
cueBeam-0.0.1.dist-info/top_level.txt
cuebeam/__init__.py
cuebeam/cueBeamCore3.py
cuebeam/cueBeamWorld.py
